slurm_mcp/__init__.py
slurm_mcp/__main__.py
slurm_mcp/calculator.py
slurm_mcp/prometheus_utils.py
slurm_mcp/s_mcp.py
slurm_mcp/s_mcp_test.py
slurm_mcp/slurm_model.py
slurm_mcp-0.0.1.dist-info/METADATA
slurm_mcp-0.0.1.dist-info/WHEEL
slurm_mcp-0.0.1.dist-info/entry_points.txt
slurm_mcp-0.0.1.dist-info/licenses/LICENSE
slurm_mcp-0.0.1.dist-info/RECORD
