Metadata-Version: 2.4
Name: slurm-mcp
Version: 0.0.1
Summary: Add your description here
Author-email: Fabrice Normandin <normandf@mila.quebec>
License-File: LICENSE
Requires-Python: >=3.13
Requires-Dist: fastmcp>=2.12.3
Requires-Dist: numpy>=2.3.3
Requires-Dist: pydantic>=2.11.9
Requires-Dist: rich>=14.1.0
Requires-Dist: sarc
